numbarrow/__init__.py
numbarrow/core/__init__.py
numbarrow/core/adapters.py
numbarrow/core/configurations.py
numbarrow/core/is_null.py
numbarrow/core/mapinarrow_factory.py
numbarrow/utils/__init__.py
numbarrow/utils/arrow_array_utils.py
numbarrow/utils/utils.py
numbarrow-0.1.2.dist-info/LICENSE
numbarrow-0.1.2.dist-info/METADATA
numbarrow-0.1.2.dist-info/WHEEL
numbarrow-0.1.2.dist-info/top_level.txt
numbarrow-0.1.2.dist-info/RECORD
