Metadata-Version: 2.1
Name: numbarrow
Version: 0.1.2
Author: Mikhail Goykhman
License: MIT License (with Citation Clause)
Keywords: pyarrow,pyspark,numba,numpy
Requires-Python: >=3.10
License-File: LICENSE
Requires-Dist: numba<0.64.0,>=0.60.0
Requires-Dist: pyspark<4.0.0,>=3.3.0
Requires-Dist: pandas>=1.5.0
Requires-Dist: pyarrow<=15.0.0
